pandemy/__init__.py
pandemy/_dataframe.py
pandemy/_datetime.py
pandemy/databasemanager.py
pandemy/exceptions.py
pandemy/sqlcontainer.py
Pandemy-1.2.0.dist-info/LICENSE
Pandemy-1.2.0.dist-info/METADATA
Pandemy-1.2.0.dist-info/WHEEL
Pandemy-1.2.0.dist-info/top_level.txt
Pandemy-1.2.0.dist-info/RECORD
